hello_world/__init__.py
hello_world/cli.py
hello_world_package_austi-0.1.0.dist-info/licenses/LICENSE
hello_world_package_austi-0.1.0.dist-info/METADATA
hello_world_package_austi-0.1.0.dist-info/WHEEL
hello_world_package_austi-0.1.0.dist-info/entry_points.txt
hello_world_package_austi-0.1.0.dist-info/top_level.txt
hello_world_package_austi-0.1.0.dist-info/RECORD
